edu_rdm_integration/__init__.py
edu_rdm_integration/apps.py
edu_rdm_integration/models.py
edu_rdm_integration/routers.py
edu_rdm_integration/collect_and_export_data/__init__.py
edu_rdm_integration/collect_and_export_data/apps.py
edu_rdm_integration/collect_and_export_data/models.py
edu_rdm_integration/collect_and_export_data/migrations/0001_initial.py
edu_rdm_integration/collect_and_export_data/migrations/0002_auto_20250204_1413.py
edu_rdm_integration/collect_and_export_data/migrations/0003_auto_20250704_0725.py
edu_rdm_integration/collect_and_export_data/migrations/__init__.py
edu_rdm_integration/core/__init__.py
edu_rdm_integration/core/consts.py
edu_rdm_integration/core/enums.py
edu_rdm_integration/core/helpers.py
edu_rdm_integration/core/mapping.py
edu_rdm_integration/core/operations.py
edu_rdm_integration/core/redis_cache.py
edu_rdm_integration/core/signals.py
edu_rdm_integration/core/storages.py
edu_rdm_integration/core/typing.py
edu_rdm_integration/core/utils.py
edu_rdm_integration/core/registry/__init__.py
edu_rdm_integration/core/registry/actions.py
edu_rdm_integration/core/registry/apps.py
edu_rdm_integration/core/registry/ui.py
edu_rdm_integration/core/registry/templates/ui-js/start-task.js
edu_rdm_integration/migrations/0001_initial.py
edu_rdm_integration/migrations/0002_init_data_uploadstatus.py
edu_rdm_integration/migrations/0003_create_index_file_upload_status.py
edu_rdm_integration/migrations/0004_uploaderclientlog.py
edu_rdm_integration/migrations/0005_auto_20231204_1224.py
edu_rdm_integration/migrations/0006_request_status_data.py
edu_rdm_integration/migrations/0007_delete_upload_status.py
edu_rdm_integration/migrations/0008_transferredentity.py
edu_rdm_integration/migrations/0009_auto_20240522_1619.py
edu_rdm_integration/migrations/0010_transferredentity_export_enabled.py
edu_rdm_integration/migrations/0011_exportingdatasubstageentity.py
edu_rdm_integration/migrations/0012_exportingdatasubstageattachment_attachment_size.py
edu_rdm_integration-3.27.6.dist-info/licenses/LICENSE
edu_rdm_integration-3.27.6.dist-info/METADATA
edu_rdm_integration-3.27.6.dist-info/WHEEL
edu_rdm_integration-3.27.6.dist-info/top_level.txt
edu_rdm_integration-3.27.6.dist-info/RECORD
